cpcctool/__init__.py
cpcctool/cpcc_code_docx.py
cpcctool/cpcc_count_code_lines.py
cpcctool/source_tie.py
cpcctool/txt2docx.py
cpcctool-0.0.3.dist-info/LICENSE
cpcctool-0.0.3.dist-info/METADATA
cpcctool-0.0.3.dist-info/WHEEL
cpcctool-0.0.3.dist-info/top_level.txt
cpcctool-0.0.3.dist-info/RECORD
